musicgeneration
