Metadata-Version: 2.1
Name: musicgeneration
Version: 0.10.3
Summary: diploma project
Home-page: UNKNOWN
Author: Bohdan Kulynych
License: MIT
Keywords: deep learning,neural networks,tensorflow,introduction
Platform: UNKNOWN
Classifier: Development Status :: 3 - Alpha
Classifier: License :: OSI Approved :: MIT License
Classifier: Programming Language :: Python :: 3
Classifier: Programming Language :: Python :: 3.6
